common_grpc/__init__.py
common_grpc/auth_service/auth_pb2.py
common_grpc/auth_service/auth_pb2_grpc.py
common_grpc/common/common_pb2.py
common_grpc/common/common_pb2_grpc.py
common_grpc/course_parser/courses_pb2.py
common_grpc/course_parser/courses_pb2_grpc.py
common_grpc/exchanger_cabinet/courses_pb2.py
common_grpc/exchanger_cabinet/courses_pb2_grpc.py
coursehunt_grpc-0.1.4.dist-info/METADATA
coursehunt_grpc-0.1.4.dist-info/WHEEL
coursehunt_grpc-0.1.4.dist-info/top_level.txt
coursehunt_grpc-0.1.4.dist-info/RECORD
