Metadata-Version: 2.4
Name: coursehunt-grpc
Version: 0.1.4
Summary: gRPC contracts and Python stubs for Coursehunt
Author: Dmitriy Pelevin
Author-email: dmitriy.pelevin@gmail.com
License: MIT
Requires-Dist: grpcio>=1.54.0
Requires-Dist: protobuf>=4.0.0
Dynamic: author
Dynamic: author-email
